latex_generator_itmo_kulyaskin/__init__.py
latex_generator_itmo_kulyaskin/latex_generator.py
latex_generator_itmo_kulyaskin-0.1.0.dist-info/LICENSE
latex_generator_itmo_kulyaskin-0.1.0.dist-info/METADATA
latex_generator_itmo_kulyaskin-0.1.0.dist-info/WHEEL
latex_generator_itmo_kulyaskin-0.1.0.dist-info/RECORD
